{
  "descriptionHash": "E8CB31437852D0A1DE1344CCE80582F1BD129D25B8EA4E4F09C88E3B84C44646CFB58DDB12DCE13B4DE453FB5BD3E076A595551820B168DC0DD68C8316D62E12",
  "descriptionLocation": "../../fixed.json",
  "lockFileVersion": "1.0.0",
  "kiotaVersion": "1.32.2",
  "clientClassName": "ComposioOpenApiClient",
  "typeAccessModifier": "Public",
  "clientNamespaceName": "Soenneker.Composio.OpenApiClient",
  "language": "CSharp",
  "usesBackingStore": false,
  "excludeBackwardCompatible": true,
  "includeAdditionalData": true,
  "disableSSLValidation": false,
  "serializers": [
    "Microsoft.Kiota.Serialization.Json.JsonSerializationWriterFactory",
    "Microsoft.Kiota.Serialization.Text.TextSerializationWriterFactory",
    "Microsoft.Kiota.Serialization.Form.FormSerializationWriterFactory",
    "Microsoft.Kiota.Serialization.Multipart.MultipartSerializationWriterFactory"
  ],
  "deserializers": [
    "Microsoft.Kiota.Serialization.Json.JsonParseNodeFactory",
    "Microsoft.Kiota.Serialization.Text.TextParseNodeFactory",
    "Microsoft.Kiota.Serialization.Form.FormParseNodeFactory"
  ],
  "structuredMimeTypes": [
    "application/json",
    "text/plain;q=0.9",
    "application/x-www-form-urlencoded;q=0.2",
    "multipart/form-data;q=0.1"
  ],
  "includePatterns": [],
  "excludePatterns": [],
  "disabledValidationRules": []
}